setup.py
src/Hatak_Sql.egg-info/PKG-INFO
src/Hatak_Sql.egg-info/SOURCES.txt
src/Hatak_Sql.egg-info/dependency_links.txt
src/Hatak_Sql.egg-info/namespace_packages.txt
src/Hatak_Sql.egg-info/not-zip-safe
src/Hatak_Sql.egg-info/requires.txt
src/Hatak_Sql.egg-info/top_level.txt
src/haplugin/__init__.py
src/haplugin/sql/__init__.py
src/haplugin/sql/driver.py
src/haplugin/sql/fixtures.py
src/haplugin/sql/models.py
src/haplugin/sql/plugin.py
src/haplugin/sql/testing.py