Metadata-Version: 1.0
Name: Hatak-Sql
Version: 0.1.12
Summary: SqlAlchemy plugin for Hatak.
Home-page: UNKNOWN
Author: UNKNOWN
Author-email: UNKNOWN
License: Apache License 2.0
Platform: UNKNOWN
